setup.cfg
setup.py
bin/blockstack
blockstore_client/__init__.py
blockstore_client/blockstore_cli.py
blockstore_client/client.py
blockstore_client/config.py
blockstore_client/parsing.py
blockstore_client/schemas.py
blockstore_client/spv.py
blockstore_client/storage.py
blockstore_client/user.py
blockstore_client/utils.py
blockstore_client/version.py
blockstore_client.egg-info/PKG-INFO
blockstore_client.egg-info/SOURCES.txt
blockstore_client.egg-info/dependency_links.txt
blockstore_client.egg-info/not-zip-safe
blockstore_client.egg-info/requires.txt
blockstore_client.egg-info/top_level.txt
blockstore_client/drivers/__init__.py
blockstore_client/drivers/dht.py
blockstore_client/drivers/disk.py
blockstore_client/drivers/s3.py