Metadata-Version: 1.1
Name: blockstore-client
Version: 0.0.12.10
Summary: Python client library for Blockstore
Home-page: https://github.com/blockstack/blockstore-client
Author: Blockstack.org
Author-email: support@blockstack.org
License: GPLv3
Download-URL: https://github.com/blockstack/blockstore-client/archive/master.zip
Keywords: blockchain bitcoin btc cryptocurrency name key value store data
Platform: UNKNOWN
Classifier: Intended Audience :: Developers
Classifier: License :: OSI Approved :: GNU General Public License v3 (GPLv3)
Classifier: Operating System :: OS Independent
Classifier: Programming Language :: Python
Classifier: Topic :: Internet
Classifier: Topic :: Security :: Cryptography
Classifier: Topic :: Software Development :: Libraries :: Python Modules
